docs/source/conf.py
wdphoto/__init__.py
wdphoto/fit.py
wdphoto/interpolator.py
wdphoto/tests.py
wdphoto/utils.py
wdphoto/data/laplata/CO_Hdef_Massive.csv
wdphoto/data/laplata/CO_Hrich_Massive.csv
wdphoto/data/laplata/CO_models.csv
wdphoto/data/laplata/He_models.csv
wdphoto/data/laplata/ONe_Hdef_Massive.csv
wdphoto/data/laplata/ONe_Hrich_Massive.csv
wdphoto/data/laplata/ONe_models.csv
wdphoto/data/laplata/allwd.csv
wdphoto/data/laplata/formatter.ipynb
wdphoto/data/laplata/high_mass/CO_110_Hdef_0_02.dat
wdphoto/data/laplata/high_mass/CO_110_Hrich_0_02.dat
wdphoto/data/laplata/high_mass/CO_116_Hdef_0_02.dat
wdphoto/data/laplata/high_mass/CO_116_Hrich_0_02.dat
wdphoto/data/laplata/high_mass/CO_123_Hdef_0_02.dat
wdphoto/data/laplata/high_mass/CO_123_Hrich_0_02.dat
wdphoto/data/laplata/high_mass/CO_129_Hdef_0_02.dat
wdphoto/data/laplata/high_mass/CO_129_Hrich_0_02.dat
wdphoto/data/laplata/high_mass/ONe_110_Hdef_0_02.dat
wdphoto/data/laplata/high_mass/ONe_110_Hrich_0_02.dat
wdphoto/data/laplata/high_mass/ONe_116_Hdef_0_02.dat
wdphoto/data/laplata/high_mass/ONe_116_Hrich_0_02.dat
wdphoto/data/laplata/high_mass/ONe_123_Hdef_0_02.dat
wdphoto/data/laplata/high_mass/ONe_123_Hrich_0_02.dat
wdphoto/data/laplata/high_mass/ONe_129_Hdef_0_02.dat
wdphoto/data/laplata/high_mass/ONe_129_Hrich_0_02.dat
wdphoto/data/warwick_da/500_3D
wdphoto/data/warwick_da/550_3D
wdphoto/data/warwick_da/600_3D
wdphoto/data/warwick_da/650_3D
wdphoto/data/warwick_da/700_3D
wdphoto/data/warwick_da/750_3D
wdphoto/data/warwick_da/800_3D
wdphoto/data/warwick_da/850_3D
wdphoto/data/warwick_da/900_3D
wdphoto/data/warwick_da/warwick_cache_table.csv
wdphoto/data/warwick_da/.ipynb_checkpoints/500_3D-checkpoint
wdphoto/data/warwick_da/.ipynb_checkpoints/550_3D-checkpoint
wdphoto/data/warwick_da/.ipynb_checkpoints/600_3D-checkpoint
wdphoto/data/warwick_da/.ipynb_checkpoints/650_3D-checkpoint
wdphoto/data/warwick_da/.ipynb_checkpoints/700_3D-checkpoint
wdphoto/data/warwick_da/.ipynb_checkpoints/750_3D-checkpoint
wdphoto-0.2.12.dist-info/LICENSE
wdphoto-0.2.12.dist-info/METADATA
wdphoto-0.2.12.dist-info/WHEEL
wdphoto-0.2.12.dist-info/top_level.txt
wdphoto-0.2.12.dist-info/RECORD
