Metadata-Version: 2.1
Name: wdphoto
Version: 0.2.12
Summary: Tools for fitting white dwarf SEDs
Author-email: Stefan Arseneau <arseneausm@gmail.com>
Project-URL: Homepage, https://github.com/stefanarseneau/wdphoto
Project-URL: Issues, https://github.com/stefanarseneau/wdphoto/issues
Classifier: Programming Language :: Python :: 3
Classifier: License :: OSI Approved :: MIT License
Classifier: Operating System :: OS Independent
Requires-Python: >=3.8
License-File: LICENSE
